UGFraud/__init__.py
UGFraud/Demo/__init__.py
UGFraud/Demo/demo_pre.py
UGFraud/Demo/eval_Fraudar.py
UGFraud/Demo/eval_GANG.py
UGFraud/Demo/eval_Prior.py
UGFraud/Demo/eval_SVD.py
UGFraud/Demo/eval_SpEagle.py
UGFraud/Demo/eval_ZooBP.py
UGFraud/Demo/eval_fBox.py
UGFraud/Demo/testing.py
UGFraud/Detector/Fraudar.py
UGFraud/Detector/GANG.py
UGFraud/Detector/MinTree.py
UGFraud/Detector/SVD.py
UGFraud/Detector/SpEagle.py
UGFraud/Detector/ZooBP.py
UGFraud/Detector/__init__.py
UGFraud/Detector/fBox.py
UGFraud/Utils/__init__.py
UGFraud/Utils/helper.py
UGFraud/Yelp_Data/YelpChi/metadata.gz
UGFraud/Yelp_Data/YelpChi/priors.pkl
UGFraud-0.1.1.3.dist-info/LICENSE
UGFraud-0.1.1.3.dist-info/METADATA
UGFraud-0.1.1.3.dist-info/WHEEL
UGFraud-0.1.1.3.dist-info/top_level.txt
UGFraud-0.1.1.3.dist-info/RECORD
