Metadata-Version: 2.1
Name: UGFraud
Version: 0.1.1.3
Summary: An Unsupervised Graph-based Toolbox for Fraud Detection
Home-page: https://github.com/safe-graph/UGFraud
Author: Yingtong Dou, Chen Wang, Sihong Xie, Guixiang Ma, and UIC BDSC Lab
Author-email: bdscsafegraph@gmail.com
License: UNKNOWN
Download-URL: https://github.com/safe-graph/UGFraud/archive/master.zip
Keywords: fraud detection,anomaly detection,graph algorithm,data mining,security
Platform: UNKNOWN
Classifier: Programming Language :: Python :: 3.6
Classifier: Programming Language :: Python :: 3.7
Classifier: Development Status :: 5 - Production/Stable
Classifier: Intended Audience :: Education
Classifier: Intended Audience :: Financial and Insurance Industry
Classifier: Intended Audience :: Science/Research
Classifier: Intended Audience :: Developers
Classifier: Intended Audience :: Information Technology
Classifier: License :: OSI Approved :: Apache Software License
Classifier: Operating System :: OS Independent
Requires-Python: >=3.6
